Changelog.rst
LICENSE
MANIFEST.in
README.rst
requirements.txt
setup.cfg
setup.py
televize.py
televize.egg-info/PKG-INFO
televize.egg-info/SOURCES.txt
televize.egg-info/dependency_links.txt
televize.egg-info/entry_points.txt
televize.egg-info/requires.txt
televize.egg-info/top_level.txt
tests/__init__.py
tests/test_play.py
tests/test_playlists.py
tests/utils.py
tests/data/ivysilani.html
tests/data/ivysilani_no_button.html
tests/data/ivysilani_no_rel.html
tests/data/play_live/client_playlist.json
tests/data/play_live/stream_playlist.m3u